chunkdot/__init__.py
chunkdot/_cosine_similarity_top_k.py
chunkdot/chunkdot.py
chunkdot/chunkdot_sparse.py
chunkdot/utils.py
chunkdot-0.6.0.dist-info/LICENSE
chunkdot-0.6.0.dist-info/METADATA
chunkdot-0.6.0.dist-info/WHEEL
chunkdot-0.6.0.dist-info/RECORD
