Metadata-Version: 2.1
Name: chunkdot
Version: 0.6.0
Summary: Multi-threaded matrix multiplication and cosine similarity calculations.
Home-page: https://github.com/rragundez/chunkdot
License: MIT
Author: Rodrigo Agundez
Author-email: rragundez@gmail.com
Requires-Python: >=3.8,<3.12
Classifier: Intended Audience :: Developers
Classifier: Intended Audience :: Science/Research
Classifier: License :: OSI Approved :: MIT License
Classifier: Programming Language :: Python :: 3
Classifier: Programming Language :: Python :: 3.8
Classifier: Programming Language :: Python :: 3.9
Classifier: Programming Language :: Python :: 3.10
Classifier: Programming Language :: Python :: 3.11
Classifier: Topic :: Scientific/Engineering
Classifier: Topic :: Software Development
Requires-Dist: numba (>=0.57.0,<0.58.0)
Requires-Dist: numba-progress (>=0.0.4,<0.0.5)
Requires-Dist: numpy (>=1.23,<2.0)
Requires-Dist: ruff (>=0.2.1,<0.3.0)
Requires-Dist: scipy (>=1.10.1,<2.0.0)
Project-URL: Repository, https://github.com/rragundez/chunkdot
